finance_stock_scraper/ExecutionContext.py
finance_stock_scraper/QuestClient.py
finance_stock_scraper/TickerRepository.py
finance_stock_scraper/YFDataProvider.py
finance_stock_scraper/__init__.py
finance_stock_scraper/__main__.py
finance_stock_scraper/workflow.py
finance_stock_scraper/model/Intervals.py
finance_stock_scraper/model/Ticker.py
finance_stock_scraper/model/__init__.py
finance_stock_scraper-0.0.4.dist-info/LICENSE
finance_stock_scraper-0.0.4.dist-info/METADATA
finance_stock_scraper-0.0.4.dist-info/WHEEL
finance_stock_scraper-0.0.4.dist-info/top_level.txt
finance_stock_scraper-0.0.4.dist-info/RECORD
