Metadata-Version: 2.1
Name: finance-stock-scraper
Version: 0.0.4
Summary: Collect, store and access stock exchange data locally
Author: Lukas Kreussel
License: MIT License        
Project-URL: Homepage, https://github.com/LLukas22/Finance-Data-Scraper
Project-URL: Bug Tracker, https://github.com/LLukas22/Finance-Data-Scraper/issues
Classifier: Programming Language :: Python :: 3
Classifier: License :: OSI Approved :: MIT License
Classifier: Operating System :: OS Independent
Requires-Python: >=3.10
License-File: LICENSE
Requires-Dist: pytz (>=2022.1)
Requires-Dist: pandas (>=1.4.2)
Requires-Dist: yfinance (>=0.1.70)
Requires-Dist: questdb (>=1.0.0)
Requires-Dist: requests (>=2.28.1)
Requires-Dist: pandas-market-calendars (>=3.4)
Requires-Dist: tqdm (>=4.64.0)
